setup.cfg
setup.py
./__init__.py
./party.py
./party.xml
./tryton.cfg
./tests/__init__.py
./tests/test_abn.py
./tests/test_views_depends.py
./view/party_form.xml
trytonll_party_abn.egg-info/PKG-INFO
trytonll_party_abn.egg-info/SOURCES.txt
trytonll_party_abn.egg-info/dependency_links.txt
trytonll_party_abn.egg-info/entry_points.txt
trytonll_party_abn.egg-info/not-zip-safe
trytonll_party_abn.egg-info/requires.txt
trytonll_party_abn.egg-info/top_level.txt