Metadata-Version: 1.1
Name: trytonll-party-abn
Version: 3.2.0.1
Summary: Validate Australian Business Number ( ABN )
Home-page: http://www.lavalab.com.au/
Author: Lava Lab Software Pty Ltd
Author-email: vincent@lavalab.com.au
License: GPL-3
Platform: UNKNOWN
Classifier: Development Status :: 4 - Beta
Classifier: Environment :: Plugins
Classifier: Intended Audience :: Developers
Classifier: License :: OSI Approved :: GNU General Public License v3 (GPLv3)
Classifier: Natural Language :: English
Classifier: Operating System :: OS Independent
Classifier: Programming Language :: Python
Classifier: Framework :: Tryton
Classifier: Topic :: Office/Business
